testcython.cp38-win32.pyd
testcython-0.0.1.dist-info/METADATA
testcython-0.0.1.dist-info/WHEEL
testcython-0.0.1.dist-info/top_level.txt
testcython-0.0.1.dist-info/RECORD
