Metadata-Version: 2.1
Name: testcython
Version: 0.0.1
Summary: pypi test for cython package
Home-page: UNKNOWN
Author: test cython
Author-email: test@cython.com
License: MIT
Platform: UNKNOWN
Requires: cython
